odoo9_addon_crm_event_registration_partner_unique-9.0.1.0.0-py2.7-nspkg.pth
odoo9_addon_crm_event_registration_partner_unique-9.0.1.0.0.dist-info/DESCRIPTION.rst
odoo9_addon_crm_event_registration_partner_unique-9.0.1.0.0.dist-info/METADATA
odoo9_addon_crm_event_registration_partner_unique-9.0.1.0.0.dist-info/RECORD
odoo9_addon_crm_event_registration_partner_unique-9.0.1.0.0.dist-info/WHEEL
odoo9_addon_crm_event_registration_partner_unique-9.0.1.0.0.dist-info/metadata.json
odoo9_addon_crm_event_registration_partner_unique-9.0.1.0.0.dist-info/namespace_packages.txt
odoo9_addon_crm_event_registration_partner_unique-9.0.1.0.0.dist-info/top_level.txt
odoo_addons/crm_event_registration_partner_unique/README.rst
odoo_addons/crm_event_registration_partner_unique/__init__.py
odoo_addons/crm_event_registration_partner_unique/__openerp__.py
odoo_addons/crm_event_registration_partner_unique/i18n/es.po
odoo_addons/crm_event_registration_partner_unique/tests/__init__.py
odoo_addons/crm_event_registration_partner_unique/tests/test_crm_deduplicate_event_unique.py
odoo_addons/crm_event_registration_partner_unique/wizards/__init__.py
odoo_addons/crm_event_registration_partner_unique/wizards/partner_merge.py
